{
  "path": "/aloha-io/title-14/chapter-245/section-245-52/",
  "title": "Alteration of packaging prohibited",
  "type": "hrs_section",
  "structure": {
    "volume": "4",
    "chapter": "245",
    "section": "245-52"
  },
  
  "prev": "https://sammade.github.io/aloha-io/title-14/chapter-245/section-245-51/",
  
  
  "next": "https://sammade.github.io/aloha-io/title-14/chapter-245/section-245-53/",
  
  "context": "ยง245-52 Alteration of packaging prohibited. It shall be unlawful for an entity to alter the package of any cigarettes, prior to sale or distribution to remove, conceal, or obscure: (1) Any statement, label, stamp, sticker, or notice indicating that the manufacturer did not intend the cigarettes to be sold, distributed, or used in the United States, including but not limited to labels stating &amp;ldquo;for export only&amp;rdquo;, &amp;ldquo;U.S. tax-exempt&amp;rdquo;, &amp;ldquo;for use outside U.S.&amp;rdquo;, or similar wording; or (2) Any health warning that is not specified in or does not conform with the requirements of the federal Cigarette Labeling and Advertising Act, title 15 U.S.C. section 1333. [L 2000, c 201, pt of ยง1; am L 2003, c 77, ยง5] "
}