{
  "path": "https://sammade.github.io/aloha-io/title-13/chapter-225m/",
  "title": "State Planning",
  "volume": "13",
  "chapter": "225M",
  "section": "",
  "context": "CHAPTER 225M STATE PLANNING Section 225M-1 Purpose 225M-2 Office of planning, establishment; responsibilities 225M-3 Cooperation 225M-4 Allocation of funds 225M-5 to 7 Repealed Note State goal for affordable rental housing units; special action team (terminated December 31, 2019); annual reports to 2017-2019 legislature. L 2016, c 127. ",
  "children" : [
    

    
      
      
      
      
      
        
{
    "path": "https://sammade.github.io/aloha-io/title-13/chapter-225m/section-225m-1/",
    "title": "225M-1 Purpose"
}

        ,
      
        
{
    "path": "https://sammade.github.io/aloha-io/title-13/chapter-225m/section-225m-2/",
    "title": "225M-2 Office of planning, establishment; responsibilities"
}

        ,
      
        
{
    "path": "https://sammade.github.io/aloha-io/title-13/chapter-225m/section-225m-3/",
    "title": "225M-3 Cooperation"
}

        ,
      
        
{
    "path": "https://sammade.github.io/aloha-io/title-13/chapter-225m/section-225m-4/",
    "title": "225M-4 Allocation of funds"
}

        ,
      
        
{
    "path": "https://sammade.github.io/aloha-io/title-13/chapter-225m/section-225m-5/",
    "title": "225M-5 to 7 Repealed"
}

        ,
      
        
{
    "path": "https://sammade.github.io/aloha-io/title-13/chapter-225m/section-225m-6/",
    "title": "Chapter 225M State Planning"
}

        
      
    
  ]
}



