{
  "path": "/aloha-io/title-23/chapter-425e/section-425e-116/",
  "title": "Resignation of registered agent",
  "type": "hrs_section",
  "structure": {
    "volume": "8",
    "chapter": "425E",
    "section": "425E-116"
  },
  
  "prev": "https://sammade.github.io/aloha-io/title-23/chapter-425e/section-425e-115/",
  
  
  "next": "https://sammade.github.io/aloha-io/title-23/chapter-425e/section-425e-117/",
  
  "context": "ยง425E-116** Resignation of registered agent.** A registered agent may resign from the registered agent&amp;rsquo;s appointment by complying with the requirements of section 425R-10. [L 2003, c 210, pt of ยง1; am L 2009, c 55, ยง42] "
}