{
  "path": "/aloha-io/title-20/chapter-363/section-363-4/",
  "title": "Establishment of cemeteries on Hawaii, Kauai, Maui, Molokai, and Lanai",
  "type": "hrs_section",
  "structure": {
    "volume": "7",
    "chapter": "363",
    "section": "363-4"
  },
  
  "prev": "https://sammade.github.io/aloha-io/title-20/chapter-363/section-363-3_5/",
  
  
  "next": "https://sammade.github.io/aloha-io/title-20/chapter-363/section-363-5/",
  
  "context": "§363-4 Establishment of cemeteries on Hawaii, Kauai, Maui, Molokai, and Lanai. The department of land and natural resources shall set aside, or acquire by exchange, purchase, or condemnation, in the manner provided by law, land suitable for the establishing of veterans cemeteries on the islands of Hawaii, Maui, Kauai, Molokai, and Lanai. [L 1947, c 214, §1; RL 1955, §348-1; am L Sp 1959 2d, c 1, §21; am L 1961, c 132, §2; HRS §363-4; am L 1978, c 58, §1; am L 1997, c 23, §1] "
}