{
  "path": "https://sammade.github.io/aloha-io/title-19/chapter-321/",
  "title": "Department of Health",
  "volume": "19",
  "chapter": "321",
  "section": "",
  "context": "TITLE 19. HEALTH Chapter 321 Department of Health 321C Office of Language Access 321D Interdepartmental Cluster for Services to Children 321E Dispersal Review Council&amp;ndash;Repealed 321F Office of the Aloha Health Corps&amp;ndash;Repealed 321G California-Hawaii Cooperative Commission&amp;ndash;Repealed 321H Neurotrauma 322 Nuisances; Sanitary Regulations 322H Hawaii Health Authority 323 Hospitals and Medical Facilities 323B Health Care Privacy Harmonization Act 323C Privacy of Health Care Information&amp;ndash;Repealed 323D Health Planning and Resources Development and Health Care Cost Control 323F Hawaii Health Systems Corporation 323G Hospital Discharge Planning&amp;ndash;Designation of a Caregiver 324 Medical Research; Morbidity and Mortality Information 325 Infectious and Communicable Diseases 326 Hansen&amp;rsquo;s Disease 327 Medical and Research Use of Bodies 327C Death 327D Medical Treatment Decisions&amp;ndash;Repealed 327E Uniform Health-Care Decisions Act (Modified) 327F Medical Treatment Decisions for Psychotic Disorders&amp;ndash; Repealed 327G Advance Mental Health Care Directives 327H Pain Patient&amp;rsquo;s Bill of Rights 327K Provider Orders for Life-Sustaining Treatment 328 Food, Drugs, and Cosmetics 328A Water, Furnishing Potable&amp;ndash;Repealed 328B Return-for-Credit-and-Reuse of Prescription Drugs&amp;ndash; Repealed 328C Donation of Pharmaceuticals and Health Care Supplies 328D Bottled Water 328E Intoxicating Compounds 328J Smoking 328K Smoking&amp;ndash;Repealed 328L Hawaii Tobacco Settlement Moneys 329 Uniform Controlled Substances Act 329B Substance Abuse Testing 329C Imitation Controlled Substances Act 329D Medical Marijuana Dispensary System 329E Overdose Prevention and Emergency Response Act 330 Poisons, Sale of 330C Hawaii Poison Prevention Packaging Act 331 Radium for Medical and Surgical Purposes&amp;ndash;Repealed 332 Mattresses, Manufacture, Etc., and Sale of 332D Polybrominated Diphenyl Ethers 333 Mental Retardation&amp;ndash;Repealed 333E Developmental Disabilities 333F Services for Persons with Developmental or Intellectual Disabilities 334 Mental Health, Mental Illness, Drug Addiction, and Alcoholism 334B Utilization Review and Managed Care of Mental Health, Alcohol, or Drug Abuse Treatment 334D Diversion Program for Chemically Dependent Nurses 334E Rights of Recipients of Mental Health Services 335 Interstate Compact on Mental Health 336 Deportation and Transfer of Alien and Nonresident Public Charges 337 Uniform Act for the Extradition of Persons of Unsound Mind 338 Vital Statistics 339 Litter Control 339D Electronic Waste and Television Recycling and Recovery Act 339K Northwest Interstate Compact on Low-Level Radioactive Waste Management 340 Hawaii Waste Management&amp;ndash;Repealed 340A Solid Waste 340B Wastewater Treatment Personnel 340E Safe Drinking Water 340F Hawaii Law for Mandatory Certification of Public Water System Operators 341 Environmental Quality Control 342 Environmental Quality&amp;ndash;Repealed 342B Air Pollution Control 342C Ozone Layer Protection 342D Water Pollution 342E Nonpoint Source Pollution Management and Control 342F Noise Pollution 342G Integrated Solid Waste Management 342H Solid Waste Pollution 342I Special Wastes Recycling 342J Hazardous Waste 342L Underground Storage Tanks 342N Used Oil Transport, Recycling, and Disposal&amp;ndash;Repealed 342P Asbestos and Lead 343 Environmental Impact Statements 343D Hawaii Environmental Disclosure Law&amp;ndash;Repealed 344 State Environmental Policy Note Pacific-Asia institute for resilience and sustainability. L 2014, c 229. CHAPTER 321 DEPARTMENT OF HEALTH Part I. General and Administrative Provisions Section 321-1 General powers and duties of the department 321-1.1 Development of environmental goals and objectives 321-1.3 Domestic violence and sexual assault special fund 321-1.4 Office of health care assurance special fund; deposits; expenditures 321-1.5 Primary health care incentive program; establishment 321-1.6 Additional duties of the director 321-1.65 Community health centers special fund 321-1.7 Public health nursing services program 321-1.8 Inspections; public notice 321-1.9 Inspections; visits; state-licensed or state-certified care facilities 321-2 General office 321-2.5 Volunteer medical assistance personnel 321-3 Repealed 321-4 Agents and inspectors 321-4.3 Epidemiologists 321-4.5 Inspection of food establishments 321-4.6 Advisory council on food protection practices; created 321-4.7 Producers of hand-pounded poi; exemption 321-5 Contract for exchange of Hawaii personnel 321-6 Repealed 321-6.5 Clinical laboratory test results 321-7 Disbursement of moneys 321-8 Repealed 321-9 Seal, rules and regulations 321-10 Rules, adoption, effect 321-10.5 Agricultural processing facilities; permits; priority 321-11 Subjects of health rules, generally 321-11.1 Medically accurate sexuality health education 321-11.2 Adult foster homes 321-11.3 Repealed 321-11.4 Fees for electronic applications and payments 321-11.5 Establishment of fees 321-11.51 Sanitation permits; transfer 321-11.6 Genetically modified organisms 321-11.7 Repealed 321-11.8 Care homes; liability insurance; coverage 321-11.9 Dental health facilities; health care facilities; use of latex gloves 321-12 Barbers, hairdressers, cosmeticians, cosmetologists, and beauticians 321-12.2 Tanning facilities; minors; penalties 321-12.5 Certified forensic examination fees 321-13 Regulation of certain other occupations 321-13.5 Certified nurse aides; investigations of abuse and neglect 321-14 License to practice certain occupations 321-14.5 Hospitals; licensing 321-14.8 Home care agencies; licensing 321-15 Biennial registration; fees, failure to register; denial, suspension, or revocation of a license 321-15.1 Definitions 321-15.2 Background checks 321-15.3 Criminal history disclosure of prospective care home resident 321-15.5 Repealed 321-15.6 Adult residential care homes; licensing 321-15.61 Adult residential care homes expanded admissions 321-15.62 Expanded adult residential care homes; licensing 321-15.63 Hospice services 321-15.7 Penalty 321-15.8 Repealed 321-15.9 Developmental disabilities residential services 321-16, 16.1 Repealed 321-16.5 Special treatment facilities 321-16.6 Therapeutic living programs 321-17 Vessels to carry diseased persons; penalty 321-18 Penalty 321-19 Delegation to counties 321-20 Remedies 321-21 Infectious wastes; management and disposal 321-22 Long term care service development fund established 321-22.5 Trauma system special fund 321-23 Catastrophic and traumatic emergency response program established 321-23.3 Volunteer emergency medical disaster response personnel 321-23.6 Rapid identification documents 321-24 to 26 Repealed 321-26.5 Environmentally-sensitive cleaning and maintenance products for use in public schools; approved list of products 321-27 Sanitation and environmental health special fund 321-27.5 Audit of sanitation branch 321-28 Traumatic brain injury advisory board 321-29 Epidemiologic investigations 321-30 Human placenta 321-30.1 Medical marijuana registry and regulation special fund; established 321-30.2 Civil monetary penalty special fund Part II. Preventive Medicine 321-31 Functions of the department 321-32 Epidemiological specialists 321-33 Shaken baby syndrome 321-34 Cytomegalovirus public education 321-35 Department of education student physical examination follow-up assistance and consultations Part IIA. Child Abuse and Neglect Prevention 321-36 Definitions 321-37 Child abuse and neglect secondary prevention programs 321-38 Hawaii children&amp;rsquo;s trust fund advisory committee Part III. Cancer Control 321-41 Educational program 321-42 Tumor clinics 321-43 Statistical activities 321-44 Repealed 321-45 Cancer examination 321-46 Breast density mammography results; report and notification Part IV. Children with Special Health Needs 321-51 Department to administer part 321-52 Powers, duties, and activities of the department 321-52.5 Repealed 321-53 Funds 321-54 Application of part Part V. Dental Health 321-61 Dental health 321-62 General duties of department 321-63 Director&amp;rsquo;s specific duties and powers Part VI. Industrial Hygiene 321-71 Industrial hygiene 321-72 Sources of ionizing radiation; federal-state agreements Part VII. Nutrition 321-81 Nutrition 321-82 Field nutritionist, rural Oahu Part VIII. Home Health Services 321-91 Program of home health services 321-92 Fees for services 321-93 Home health services; source of funds; disposition of receipts Part IX. Systematic Hearing and Vision Program 321-101 Systematic hearing and vision program Part IXA. Prevention of Blindness 321-106 Prevention of blindness at childbirth Part X. Sexually Transmitted Diseases 321-111 Sexually transmitted disease prevention program 321-112 to 114 Repealed 321-115 Prophylactics Part XI. Chronic Renal Disease&amp;ndash;Repealed 321-121 to 123 Repealed Part XII. Safety Glazing of Glass&amp;ndash;Repealed 321-131 to 137 Repealed Part XIII. Emergency services&amp;ndash;Repealed 321-151 Repealed Part XIV. Blood Alcohol 321-161 Chemical testing for alcohol concentration or drug content Part XV. Mental Health Services for Children and Youth 321-171 Children&amp;rsquo;s mental health services; department responsibility 321-171.5 Employees of the department of health, its providers and subcontractors; background checks 321-172 Children&amp;rsquo;s mental health services branch 321-173 Community mental health services for children and youth 321-174 Coordination of services with department of education 321-175 Statewide children&amp;rsquo;s mental health services plan 321-176 Biennial review of progress 321-177 Rules Part XVI. Substance Abuse 321-191 Definitions 321-192 Substance abuse program 321-192.5 Substance abuse treatment monitoring program 321-193 Duties and responsibilities of department 321-193.5 Interagency coordination 321-193.7 Clean and sober homes registry 321-194 State advisory commission 321-195 Annual report to the legislature 321-196 Rules 321-197 Personnel 321-198 State funding of substance abuse agencies Part XVII. Smoking in Public Places&amp;ndash;Repealed 321-201 to 206 Repealed Part XVIIA. Tobacco Products 321-211 Definitions 321-212 Tobacco products; possession or consumption prohibited 321-213 Exemptions 321-214 Enforcement; rules Part XVIII. State Comprehensive Emergency Medical Services System 321-221 Findings and purpose 321-222 Definitions 321-223 State comprehensive emergency medical services system, establishment 321-224 Department of health, functions, duties 321-225 The state emergency medical services advisory Committee 321-225.5 Fall prevention and early detection coordinator 321-226 Emergency medical services and systems, standards 321-227 Regulation of ambulances 321-228 Emergency medical services; counties 321-228.5 Renumbered 321-228.6 Renumbered 321-229 Emergency medical services personnel, training programs 321-229.5 Renumbered 321-230 Technical assistance, data collection, evaluation 321-231 Grants 321-232 Revenues; deposit into state general fund 321-233 Rules 321-234 Emergency medical services special fund 321-235 Immunity and limitation on liability for emergency aeromedical services 321-236 Emergency medical services; use of latex gloves prohibited Part XIX. School Health Services Program&amp;ndash;Repealed 321-241 to 246 Repealed Part XX. Agent Orange&amp;ndash;Repealed 321-261 to 271 Repealed Part XXI. Hemophilia 321-281 Financial assistance fund for hemophilia 321-282 General duties of the department Part XXII. Newborn Metabolic Screening 321-291 Tests for phenylketonuria, hypothyroidism, and other metabolic diseases Part XXIIA. Newborn Pulse Oximetry Screening 321-296 Newborn pulse oximetry screening Part XXIII. Health Education 321-301 Bilingual health education aide program; establishment Part XXIV. Environmentally-Related Illness and Injury 321-311 Environmentally-related illness and injury surveillance 321-311.5 Renumbered 321-312 Definition of environmentally-related illness or injury 321-313 Definition of health care professional 321-314 Reports to the department 321-315 Confidentiality 321-316 Immunity from liability 321-317 Rules Part XXV. Maternal and Child Health Program 321-321 Purpose 321-322 Administration of programs 321-323 Definitions 321-324 Powers of the department 321-325 Agreements 321-326 Rules 321-327 Hawaii home visiting program; established Part XXVI. Prenatal Health Care 321-331 Prenatal health care; authority Part XXVII. Child Death Review 321-341 Multidisciplinary and multiagency reviews 321-342 Definitions 321-343 Access to information; use of child death review information; protections 321-344 Exception 321-345 Repealed 321-345.5 Child death reviews; reports 321-346 Immunity from liability Part XXVIII. Infants and Toddlers 321-351 Definitions 321-352 Early intervention services for infants and toddlers with special needs 321-352.2 Early language services for children who are deaf, hard of hearing, or deaf-blind 321-353 Hawaii early intervention coordinating council; establishment 321-354 Rules 321-355 Early intervention special fund 321-356 Repealed 321-357 Early intervention fund; purpose and use Part XXIX. Statewide Newborn Hearing Screening Program 321-361 Definitions 321-362 Duties 321-362.5 Screening for hearing impairment 321-363 Rules Part XXX. Tattoo Artists 321-371 Purpose 321-372 Definitions 321-373 Regulation of tattoo artists 321-373.5 Permit; required for tattoo shop and temporary locations 321-374 License required; exemptions 321-375 Examination; fees required 321-376 Repealed 321-377 Suspension or revocation of permit or license 321-378 Repealed 321-379 Enforcement; penalties 321-380 Repealed 321-381 Biennial renewal; failure to renew 321-382 Fees 321-383 Repealed Part XXXI. Midwives&amp;ndash;Repealed 321-391 to 398 Repealed Part XXXII. Food Safety Consultative and Education Program 321-401 Findings and purpose 321-402 Food safety consultative and education program 321-403 Food safety control system 321-404 Public information monitoring system 321-405 Confidentiality of information Part XXXIII. Indoor Air Quality 321-411 Definitions 321-412 Indoor air quality program 321-413 General functions, powers, and duties of the department Part XXXIV. Birth Defects Program 321-421 Definitions 321-422 Birth defects program 321-423 Confidentiality of data 321-424 Rules 321-425 Requests for information 321-426 Birth defects special fund Part XXXV. Case Management Services for Medically Fragile Children 321-431 Definitions 321-432 Case management services for medically fragile children Part XXXVI. Emergency Response Stockpile 321-441 Definitions 321-442 Exemption from certain laws and rules Part XXXVII. Domestic Violence Fatality Review 321-471 Definitions 321-472 Multidisciplinary and multiagency reviews 321-473 Access to information 321-474 Exception 321-475 Use of domestic violence fatality review information and records 321-476 Immunity from liability Part XXXVIII. Home and Community-Based Case Management Agencies and Community Care Foster Family Homes 321-481 Definitions 321-482 Home and community-based case management agency, authority over and evaluation of 321-483 Community care foster family home, authority over and evaluation of 321-484 Repealed 321-485 Penalty Part XXXIX. Services to Adults 321-491 Purpose 321-492 Definitions 321-493 Day care centers for disabled and aged persons 321-494 Purchase of service 321-495 Penalty 321-496 Repealed Part XL. Mortality Review of Deaths of Persons with Developmental or Intellectual Disabilities 321-501 Multidisciplinary and multiagency mortality reviews 321-502 Definitions 321-503 Access to information 321-504 Exception 321-505 Use of information and records from mortality reviews of deaths of persons with developmental or intellectual disabilities 321-506 Immunity from liability Part XLI. Compassionate Care for Sexual Assault Victims 321-511 Definitions 321-512 Compassionate care 321-513 Enforcement; administrative penalties 321-514 Rules Part XLII. Stroke Care 321-531 Definitions 321-532 Stroke system of care; department duties 321-533 Stroke database 321-534 Confidential information Part XLIII. Durable Medical Equipment Supplier License Program 321-541 Title 321-542 Definitions 321-543 Licensing 321-544 License fee 321-545 Exemptions 321-546 Rules 321-547 Severability Note Adolescent school-based substance abuse treatment programs. L 2006, c 268. Announced and unannounced visits and unannounced inspections by the department of health on state-licensed or state-certified care facilities; reports to 2017-2019 legislature. L 2016, c 184, §8. Certain positions in the adult mental health division of the department of health are exempt from the civil service requirements of chapter 76, for three calendar years commencing on July 1, 2016, unless extended by legislative act. L 2016, c 79, §3. Concussion educational program under department of education. L 2012, c 197; L 2016, c 262. Continuum of dental care; community-based dental health clinics. L 2006, c 199. Department of health to conduct study on distribution of revenues derived from birth, marriage, divorce, and death certificates fees; study to be submitted to legislature and governor no later than November 1, 2016. L 2016, c 43, §§10, 11. Department of health to request funding for the permanent position that facilitates the licensing of home care agencies as part of its annual budget request, beginning with fiscal year 2015-2016. L 2014, c 125, §4. Distribution of cigarette tax revenues study; findings and recommendations to legislature and governor by November 1, 2016. L 2016, c 86. Environmental response revolving fund; reports on fund expenditures, encumbrances, and revenues to 2016-2017 legislature. L 2015, c 185, §9. Equitable referral system for discharge of medicaid patients from hospitals, nursing homes, and long-term care facilities. L 2012, c 211. Legislative oversight working group; improvement of the medical marijuana dispensary system (ceases to exist June 30, 2018); reports to 2017-2018 legislature. L 2016, c 230, §23. Long-term care public education and awareness campaign; report to 2017 legislature. L 2014, c 151, §7. Maui regional system facilities; transfer of health care services to a nonprofit management entity; governor to inform the president of the senate and the speaker of the house of representatives of transfer completion dates. L 2015, c 103, §4. Medical marijuana dispensary system; personnel and contracts, exemption from chapter 76 (July 1, 2015, to June 30, 2017). L 2015, c 241, §14. Permanent or temporary exempt positions authorized; exemptions expire three years after July 1, 2016, unless extended by legislative act. L 2016, c 79, §2. Repayment plan and schedule for deposits into medical marijuana registry and regulation special fund (not later than July 1, 2017). L 2015, c 241, §12. State innovation waiver task force; health care reform plan; reports to 2015-2017 legislature (repealed June 30, 2017). L 2014, c 158; L 2015, c 184. Working group on age-appropriate development for children from birth to age five years who are deaf, hard of hearing, or deaf-blind; reports to 2017-2018 legislature (ceases to exist June 30, 2018). L 2016, c 177, §3. Working group on documentation for state civil identification card; reports to 2016-2017 legislature (dissolved on June 30, 2017). L 2015, c 243. Cross References Coordination and development of caregiver support services, see §349-15. Drug demand reduction assessments; special fund, see §706-650. Hawaii health authority, see chapter 322H. Hawaii health corps, see chapter 309H. Health and dental insurance data; mandatory reporting for certain insurers, see §323D-18.5. Health care-associated infection reporting, see §325-2.5. Home and community-based case management agencies and community care foster family homes, see §§346-331 to 336. Hospital sustainability program, see chapter 346G. Kahuku medical center; designation as a rural hospital, see §346-53.8. Long-term care financing, see chapter 346C. Medicaid contracts; nonprofit and for-profit reporting requirements, see §103F-107. Medical marijuana; economic and other data; collection, see §201-13.9. Medical marijuana testing and research programs, see §304A-1865. Nursing facility sustainability program, see chapter 346F. Regulatory licensing of certain health related professions or occupations, see title 25. Safe place for newborns, see chapter 587D. Sale of sterile syringes for the prevention of disease, see §325-21. Sex offender treatment program, see chapter 353E. State health insurance program, see chapter 431N. ",
  "children" : [
    

    
      
      
      
      
      
        
{
    "path": "https://sammade.github.io/aloha-io/title-19/chapter-321/section-321-1/",
    "title": "321-1 General powers and duties of the department"
}

        ,
      
        
{
    "path": "https://sammade.github.io/aloha-io/title-19/chapter-321/section-321-1_1/",
    "title": "321-1.1 Development of environmental goals and objectives"
}

        ,
      
        
{
    "path": "https://sammade.github.io/aloha-io/title-19/chapter-321/section-321-1_3/",
    "title": "321-1.3 Domestic violence and sexual assault special fund"
}

        ,
      
        
{
    "path": "https://sammade.github.io/aloha-io/title-19/chapter-321/section-321-1_4/",
    "title": "321-1.4 Office of health care assurance special fund; deposits; expenditures"
}

        ,
      
        
{
    "path": "https://sammade.github.io/aloha-io/title-19/chapter-321/section-321-1_5/",
    "title": "321-1.5 Primary health care incentive program; establishment"
}

        ,
      
        
{
    "path": "https://sammade.github.io/aloha-io/title-19/chapter-321/section-321-1_6/",
    "title": "321-1.6 Additional duties of the director"
}

        ,
      
        
{
    "path": "https://sammade.github.io/aloha-io/title-19/chapter-321/section-321-1_7/",
    "title": "321-1.7 Public health nursing services program"
}

        ,
      
        
{
    "path": "https://sammade.github.io/aloha-io/title-19/chapter-321/section-321-1_8/",
    "title": "321-1.8 Inspections; public notice"
}

        ,
      
        
{
    "path": "https://sammade.github.io/aloha-io/title-19/chapter-321/section-321-1_9/",
    "title": "321-1.9 Inspections; visits; state-licensed or state-certified"
}

        ,
      
        
{
    "path": "https://sammade.github.io/aloha-io/title-19/chapter-321/section-321-1_65/",
    "title": "321-1.65 Community health centers special fund"
}

        ,
      
        
{
    "path": "https://sammade.github.io/aloha-io/title-19/chapter-321/section-321-2/",
    "title": "321-2 General office"
}

        ,
      
        
{
    "path": "https://sammade.github.io/aloha-io/title-19/chapter-321/section-321-2_5/",
    "title": "321-2.5 Volunteer medical assistance personnel"
}

        ,
      
        
{
    "path": "https://sammade.github.io/aloha-io/title-19/chapter-321/section-321-3/",
    "title": "321-3 Repealed"
}

        ,
      
        
{
    "path": "https://sammade.github.io/aloha-io/title-19/chapter-321/section-321-4/",
    "title": "321-4 Agents and inspectors"
}

        ,
      
        
{
    "path": "https://sammade.github.io/aloha-io/title-19/chapter-321/section-321-4_3/",
    "title": "321-4.3 Epidemiologists"
}

        ,
      
        
{
    "path": "https://sammade.github.io/aloha-io/title-19/chapter-321/section-321-4_5/",
    "title": "321-4.5 Inspection of food establishments"
}

        ,
      
        
{
    "path": "https://sammade.github.io/aloha-io/title-19/chapter-321/section-321-4_6/",
    "title": "321-4.6 Advisory council on food protection practices; created"
}

        ,
      
        
{
    "path": "https://sammade.github.io/aloha-io/title-19/chapter-321/section-321-4_7/",
    "title": "321-4.7 Producers of hand-pounded poi; exemption"
}

        ,
      
        
{
    "path": "https://sammade.github.io/aloha-io/title-19/chapter-321/section-321-5/",
    "title": "321-5 Contract for exchange of Hawaii personnel"
}

        ,
      
        
{
    "path": "https://sammade.github.io/aloha-io/title-19/chapter-321/section-321-6/",
    "title": "321-6 Repealed"
}

        ,
      
        
{
    "path": "https://sammade.github.io/aloha-io/title-19/chapter-321/section-321-6_5/",
    "title": "321-6.5 Clinical laboratory test results"
}

        ,
      
        
{
    "path": "https://sammade.github.io/aloha-io/title-19/chapter-321/section-321-7/",
    "title": "321-7 Disbursement of moneys"
}

        ,
      
        
{
    "path": "https://sammade.github.io/aloha-io/title-19/chapter-321/section-321-8/",
    "title": "321-8 Repealed"
}

        ,
      
        
{
    "path": "https://sammade.github.io/aloha-io/title-19/chapter-321/section-321-9/",
    "title": "321-9 Seal, rules and regulations"
}

        ,
      
        
{
    "path": "https://sammade.github.io/aloha-io/title-19/chapter-321/section-321-10/",
    "title": "321-10 Rules, adoption, effect"
}

        ,
      
        
{
    "path": "https://sammade.github.io/aloha-io/title-19/chapter-321/section-321-10_5/",
    "title": "321-10.5 Agricultural processing facilities; permits; priority"
}

        ,
      
        
{
    "path": "https://sammade.github.io/aloha-io/title-19/chapter-321/section-321-11/",
    "title": "321-11 Subjects of health rules, generally"
}

        ,
      
        
{
    "path": "https://sammade.github.io/aloha-io/title-19/chapter-321/section-321-11_1/",
    "title": "321-11.1 Medically accurate sexuality health education"
}

        ,
      
        
{
    "path": "https://sammade.github.io/aloha-io/title-19/chapter-321/section-321-11_2/",
    "title": "321-11.2 Adult foster homes"
}

        ,
      
        
{
    "path": "https://sammade.github.io/aloha-io/title-19/chapter-321/section-321-11_3/",
    "title": "321-11.3 Repealed"
}

        ,
      
        
{
    "path": "https://sammade.github.io/aloha-io/title-19/chapter-321/section-321-11_4/",
    "title": "321-11.4 Fees for electronic applications and payments"
}

        ,
      
        
{
    "path": "https://sammade.github.io/aloha-io/title-19/chapter-321/section-321-11_5/",
    "title": "321-11.5 Establishment of fees"
}

        ,
      
        
{
    "path": "https://sammade.github.io/aloha-io/title-19/chapter-321/section-321-11_6/",
    "title": "321-11.6 Genetically modified organisms"
}

        ,
      
        
{
    "path": "https://sammade.github.io/aloha-io/title-19/chapter-321/section-321-11_7/",
    "title": "321-11.7 Repealed"
}

        ,
      
        
{
    "path": "https://sammade.github.io/aloha-io/title-19/chapter-321/section-321-11_8/",
    "title": "321-11.8 Care homes; liability insurance; coverage"
}

        ,
      
        
{
    "path": "https://sammade.github.io/aloha-io/title-19/chapter-321/section-321-11_9/",
    "title": "321-11.9 Dental health facilities; health care facilities; use of latex gloves"
}

        ,
      
        
{
    "path": "https://sammade.github.io/aloha-io/title-19/chapter-321/section-321-11_51/",
    "title": "321-11.51 Sanitation permits; transfer"
}

        ,
      
        
{
    "path": "https://sammade.github.io/aloha-io/title-19/chapter-321/section-321-12/",
    "title": "321-12 Barbers, hairdressers, cosmeticians, cosmetologists, and beauticians"
}

        ,
      
        
{
    "path": "https://sammade.github.io/aloha-io/title-19/chapter-321/section-321-12_2/",
    "title": "321-12.2 Tanning facilities; minors; penalties"
}

        ,
      
        
{
    "path": "https://sammade.github.io/aloha-io/title-19/chapter-321/section-321-12_5/",
    "title": "321-12.5 Certified forensic examination fees"
}

        ,
      
        
{
    "path": "https://sammade.github.io/aloha-io/title-19/chapter-321/section-321-13/",
    "title": "321-13 Regulation of certain other occupations"
}

        ,
      
        
{
    "path": "https://sammade.github.io/aloha-io/title-19/chapter-321/section-321-13_5/",
    "title": "321-13.5 Certified nurse aides; investigations of abuse and neglect"
}

        ,
      
        
{
    "path": "https://sammade.github.io/aloha-io/title-19/chapter-321/section-321-14/",
    "title": "321-14 License to practice certain occupations"
}

        ,
      
        
{
    "path": "https://sammade.github.io/aloha-io/title-19/chapter-321/section-321-14_5/",
    "title": "321-14.5 Hospitals; licensing"
}

        ,
      
        
{
    "path": "https://sammade.github.io/aloha-io/title-19/chapter-321/section-321-14_8/",
    "title": "321-14.8 Home care agencies; licensing"
}

        ,
      
        
{
    "path": "https://sammade.github.io/aloha-io/title-19/chapter-321/section-321-15/",
    "title": "321-15 Biennial registration; fees, failure to register; denial, suspension, or revocation of a license"
}

        ,
      
        
{
    "path": "https://sammade.github.io/aloha-io/title-19/chapter-321/section-321-15_1/",
    "title": "321-15.1 Definitions"
}

        ,
      
        
{
    "path": "https://sammade.github.io/aloha-io/title-19/chapter-321/section-321-15_2/",
    "title": "321-15.2 Background checks"
}

        ,
      
        
{
    "path": "https://sammade.github.io/aloha-io/title-19/chapter-321/section-321-15_3/",
    "title": "321-15.3 Criminal history disclosure of prospective care home resident"
}

        ,
      
        
{
    "path": "https://sammade.github.io/aloha-io/title-19/chapter-321/section-321-15_5/",
    "title": "321-15.5 Repealed"
}

        ,
      
        
{
    "path": "https://sammade.github.io/aloha-io/title-19/chapter-321/section-321-15_6/",
    "title": "321-15.6 Adult residential care homes; licensing"
}

        ,
      
        
{
    "path": "https://sammade.github.io/aloha-io/title-19/chapter-321/section-321-15_7/",
    "title": "321-15.7 Penalty"
}

        ,
      
        
{
    "path": "https://sammade.github.io/aloha-io/title-19/chapter-321/section-321-15_8/",
    "title": "321-15.8 Repealed"
}

        ,
      
        
{
    "path": "https://sammade.github.io/aloha-io/title-19/chapter-321/section-321-15_9/",
    "title": "321-15.9 Developmental disabilities residential services"
}

        ,
      
        
{
    "path": "https://sammade.github.io/aloha-io/title-19/chapter-321/section-321-15_61/",
    "title": "321-15.61 Adult residential care homes expanded admissions"
}

        ,
      
        
{
    "path": "https://sammade.github.io/aloha-io/title-19/chapter-321/section-321-15_62/",
    "title": "321-15.62 Expanded adult residential care homes; licensing"
}

        ,
      
        
{
    "path": "https://sammade.github.io/aloha-io/title-19/chapter-321/section-321-15_63/",
    "title": "321-15.63 Hospice services"
}

        ,
      
        
{
    "path": "https://sammade.github.io/aloha-io/title-19/chapter-321/section-321-16/",
    "title": "321-16 16.1 Repealed"
}

        ,
      
        
{
    "path": "https://sammade.github.io/aloha-io/title-19/chapter-321/section-321-16_5/",
    "title": "321-16.5 Special treatment facilities"
}

        ,
      
        
{
    "path": "https://sammade.github.io/aloha-io/title-19/chapter-321/section-321-16_6/",
    "title": "321-16.6 Therapeutic living programs"
}

        ,
      
        
{
    "path": "https://sammade.github.io/aloha-io/title-19/chapter-321/section-321-17/",
    "title": "321-17 Vessels to carry diseased persons; penalty"
}

        ,
      
        
{
    "path": "https://sammade.github.io/aloha-io/title-19/chapter-321/section-321-18/",
    "title": "321-18 Penalty"
}

        ,
      
        
{
    "path": "https://sammade.github.io/aloha-io/title-19/chapter-321/section-321-19/",
    "title": "321-19 Delegation to counties"
}

        ,
      
        
{
    "path": "https://sammade.github.io/aloha-io/title-19/chapter-321/section-321-20/",
    "title": "321-20 Remedies"
}

        ,
      
        
{
    "path": "https://sammade.github.io/aloha-io/title-19/chapter-321/section-321-21/",
    "title": "321-21 Infectious wastes; management and disposal"
}

        ,
      
        
{
    "path": "https://sammade.github.io/aloha-io/title-19/chapter-321/section-321-22/",
    "title": "321-22 Long term care service development fund established"
}

        ,
      
        
{
    "path": "https://sammade.github.io/aloha-io/title-19/chapter-321/section-321-22_5/",
    "title": "321-22.5 Trauma system special fund"
}

        ,
      
        
{
    "path": "https://sammade.github.io/aloha-io/title-19/chapter-321/section-321-23/",
    "title": "321-23 Catastrophic and traumatic emergency response"
}

        ,
      
        
{
    "path": "https://sammade.github.io/aloha-io/title-19/chapter-321/section-321-23_3/",
    "title": "321-23.3 Volunteer emergency medical disaster response personnel"
}

        ,
      
        
{
    "path": "https://sammade.github.io/aloha-io/title-19/chapter-321/section-321-23_6/",
    "title": "321-23.6 Rapid identification documents"
}

        ,
      
        
{
    "path": "https://sammade.github.io/aloha-io/title-19/chapter-321/section-321-24/",
    "title": "321-24 to 26 Repealed"
}

        ,
      
        
{
    "path": "https://sammade.github.io/aloha-io/title-19/chapter-321/section-321-26_5/",
    "title": "321-26.5 Environmentally-sensitive cleaning and maintenance products for use in public schools; approved list of products"
}

        ,
      
        
{
    "path": "https://sammade.github.io/aloha-io/title-19/chapter-321/section-321-27/",
    "title": "321-27 Sanitation and environmental health special fund"
}

        ,
      
        
{
    "path": "https://sammade.github.io/aloha-io/title-19/chapter-321/section-321-27_5/",
    "title": "321-27.5 Audit of sanitation branch"
}

        ,
      
        
{
    "path": "https://sammade.github.io/aloha-io/title-19/chapter-321/section-321-28/",
    "title": "321-28 Traumatic brain injury advisory board"
}

        ,
      
        
{
    "path": "https://sammade.github.io/aloha-io/title-19/chapter-321/section-321-29/",
    "title": "321-29 Epidemiologic investigations"
}

        ,
      
        
{
    "path": "https://sammade.github.io/aloha-io/title-19/chapter-321/section-321-30/",
    "title": "321-30 Human placenta"
}

        ,
      
        
{
    "path": "https://sammade.github.io/aloha-io/title-19/chapter-321/section-321-30_1/",
    "title": "321-30.1 Medical marijuana registry and regulation special fund; established"
}

        ,
      
        
{
    "path": "https://sammade.github.io/aloha-io/title-19/chapter-321/section-321-30_2/",
    "title": "321-30.2 Civil monetary penalty special fund"
}

        ,
      
        
{
    "path": "https://sammade.github.io/aloha-io/title-19/chapter-321/section-321-31/",
    "title": "321-31 Functions of the department"
}

        ,
      
        
{
    "path": "https://sammade.github.io/aloha-io/title-19/chapter-321/section-321-32/",
    "title": "321-32 Epidemiological specialists"
}

        ,
      
        
{
    "path": "https://sammade.github.io/aloha-io/title-19/chapter-321/section-321-33/",
    "title": "321-33 Shaken baby syndrome"
}

        ,
      
        
{
    "path": "https://sammade.github.io/aloha-io/title-19/chapter-321/section-321-34/",
    "title": "321-34 Cytomegalovirus public education"
}

        ,
      
        
{
    "path": "https://sammade.github.io/aloha-io/title-19/chapter-321/section-321-35/",
    "title": "321-35 Department of education student physical examination follow-up assistance and consultations"
}

        ,
      
        
{
    "path": "https://sammade.github.io/aloha-io/title-19/chapter-321/section-321-36/",
    "title": "321-36 Definitions"
}

        ,
      
        
{
    "path": "https://sammade.github.io/aloha-io/title-19/chapter-321/section-321-37/",
    "title": "321-37 Child abuse and neglect secondary prevention programs"
}

        ,
      
        
{
    "path": "https://sammade.github.io/aloha-io/title-19/chapter-321/section-321-38/",
    "title": "321-38 Hawaii children&#39;s trust fund advisory committee"
}

        ,
      
        
{
    "path": "https://sammade.github.io/aloha-io/title-19/chapter-321/section-321-41/",
    "title": "321-41 Educational program"
}

        ,
      
        
{
    "path": "https://sammade.github.io/aloha-io/title-19/chapter-321/section-321-42/",
    "title": "321-42 Tumor clinics"
}

        ,
      
        
{
    "path": "https://sammade.github.io/aloha-io/title-19/chapter-321/section-321-43/",
    "title": "321-43 Statistical activities"
}

        ,
      
        
{
    "path": "https://sammade.github.io/aloha-io/title-19/chapter-321/section-321-44/",
    "title": "321-44 Repealed"
}

        ,
      
        
{
    "path": "https://sammade.github.io/aloha-io/title-19/chapter-321/section-321-45/",
    "title": "321-45 Cancer examination"
}

        ,
      
        
{
    "path": "https://sammade.github.io/aloha-io/title-19/chapter-321/section-321-46/",
    "title": "321-46 Breast density mammography results; report and notification"
}

        ,
      
        
{
    "path": "https://sammade.github.io/aloha-io/title-19/chapter-321/section-321-51/",
    "title": "321-51 Department to administer part"
}

        ,
      
        
{
    "path": "https://sammade.github.io/aloha-io/title-19/chapter-321/section-321-52/",
    "title": "321-52 Powers, duties, and activities of the department"
}

        ,
      
        
{
    "path": "https://sammade.github.io/aloha-io/title-19/chapter-321/section-321-52_5/",
    "title": "321-52.5 Repealed"
}

        ,
      
        
{
    "path": "https://sammade.github.io/aloha-io/title-19/chapter-321/section-321-53/",
    "title": "321-53 Funds"
}

        ,
      
        
{
    "path": "https://sammade.github.io/aloha-io/title-19/chapter-321/section-321-54/",
    "title": "321-54 Application of part"
}

        ,
      
        
{
    "path": "https://sammade.github.io/aloha-io/title-19/chapter-321/section-321-61/",
    "title": "321-61 Dental health"
}

        ,
      
        
{
    "path": "https://sammade.github.io/aloha-io/title-19/chapter-321/section-321-62/",
    "title": "321-62 General duties of department"
}

        ,
      
        
{
    "path": "https://sammade.github.io/aloha-io/title-19/chapter-321/section-321-63/",
    "title": "321-63 Director&#39;s specific duties and powers"
}

        ,
      
        
{
    "path": "https://sammade.github.io/aloha-io/title-19/chapter-321/section-321-71/",
    "title": "321-71 Industrial hygiene"
}

        ,
      
        
{
    "path": "https://sammade.github.io/aloha-io/title-19/chapter-321/section-321-72/",
    "title": "321-72 Sources of ionizing radiation; federal-state agreements"
}

        ,
      
        
{
    "path": "https://sammade.github.io/aloha-io/title-19/chapter-321/section-321-81/",
    "title": "321-81 Nutrition"
}

        ,
      
        
{
    "path": "https://sammade.github.io/aloha-io/title-19/chapter-321/section-321-82/",
    "title": "321-82 Field nutritionist, rural Oahu"
}

        ,
      
        
{
    "path": "https://sammade.github.io/aloha-io/title-19/chapter-321/section-321-91/",
    "title": "321-91 Program of home health services"
}

        ,
      
        
{
    "path": "https://sammade.github.io/aloha-io/title-19/chapter-321/section-321-92/",
    "title": "321-92 Fees for services"
}

        ,
      
        
{
    "path": "https://sammade.github.io/aloha-io/title-19/chapter-321/section-321-93/",
    "title": "321-93 Home health services; source of funds; disposition of receipts"
}

        ,
      
        
{
    "path": "https://sammade.github.io/aloha-io/title-19/chapter-321/section-321-101/",
    "title": "321-101 Systematic hearing and vision program"
}

        ,
      
        
{
    "path": "https://sammade.github.io/aloha-io/title-19/chapter-321/section-321-106/",
    "title": "321-106 Prevention of blindness at childbirth"
}

        ,
      
        
{
    "path": "https://sammade.github.io/aloha-io/title-19/chapter-321/section-321-111/",
    "title": "321-111 Sexually transmitted disease prevention program"
}

        ,
      
        
{
    "path": "https://sammade.github.io/aloha-io/title-19/chapter-321/section-321-112/",
    "title": "321-112 to 114 Repealed"
}

        ,
      
        
{
    "path": "https://sammade.github.io/aloha-io/title-19/chapter-321/section-321-115/",
    "title": "321-115 Prophylactics"
}

        ,
      
        
{
    "path": "https://sammade.github.io/aloha-io/title-19/chapter-321/section-321-121/",
    "title": "321-121 to 123 Repealed"
}

        ,
      
        
{
    "path": "https://sammade.github.io/aloha-io/title-19/chapter-321/section-321-131/",
    "title": "321-131 to 137 Repealed"
}

        ,
      
        
{
    "path": "https://sammade.github.io/aloha-io/title-19/chapter-321/section-321-151/",
    "title": "321-151 Repealed"
}

        ,
      
        
{
    "path": "https://sammade.github.io/aloha-io/title-19/chapter-321/section-321-161/",
    "title": "321-161 Chemical testing for alcohol concentration or drug content"
}

        ,
      
        
{
    "path": "https://sammade.github.io/aloha-io/title-19/chapter-321/section-321-171/",
    "title": "321-171 Children&#39;s mental health services; department responsibility"
}

        ,
      
        
{
    "path": "https://sammade.github.io/aloha-io/title-19/chapter-321/section-321-171_5/",
    "title": "321-171.5 Employees of the department of health, its providers and subcontractors; background checks"
}

        ,
      
        
{
    "path": "https://sammade.github.io/aloha-io/title-19/chapter-321/section-321-172/",
    "title": "321-172 Children&#39;s mental health services branch"
}

        ,
      
        
{
    "path": "https://sammade.github.io/aloha-io/title-19/chapter-321/section-321-173/",
    "title": "321-173 Community mental health services for children and youth"
}

        ,
      
        
{
    "path": "https://sammade.github.io/aloha-io/title-19/chapter-321/section-321-174/",
    "title": "321-174 Coordination of services with department of education"
}

        ,
      
        
{
    "path": "https://sammade.github.io/aloha-io/title-19/chapter-321/section-321-175/",
    "title": "321-175 Statewide children&#39;s mental health services plan"
}

        ,
      
        
{
    "path": "https://sammade.github.io/aloha-io/title-19/chapter-321/section-321-176/",
    "title": "321-176 Biennial review of progress"
}

        ,
      
        
{
    "path": "https://sammade.github.io/aloha-io/title-19/chapter-321/section-321-177/",
    "title": "321-177 Rules"
}

        ,
      
        
{
    "path": "https://sammade.github.io/aloha-io/title-19/chapter-321/section-321-191/",
    "title": "321-191 Definitions"
}

        ,
      
        
{
    "path": "https://sammade.github.io/aloha-io/title-19/chapter-321/section-321-192/",
    "title": "321-192 Substance abuse program"
}

        ,
      
        
{
    "path": "https://sammade.github.io/aloha-io/title-19/chapter-321/section-321-192_5/",
    "title": "321-192.5 Substance abuse treatment monitoring program"
}

        ,
      
        
{
    "path": "https://sammade.github.io/aloha-io/title-19/chapter-321/section-321-193/",
    "title": "321-193 Duties and responsibilities of department"
}

        ,
      
        
{
    "path": "https://sammade.github.io/aloha-io/title-19/chapter-321/section-321-193_5/",
    "title": "321-193.5 Interagency coordination"
}

        ,
      
        
{
    "path": "https://sammade.github.io/aloha-io/title-19/chapter-321/section-321-193_7/",
    "title": "321-193.7 Clean and sober homes registry"
}

        ,
      
        
{
    "path": "https://sammade.github.io/aloha-io/title-19/chapter-321/section-321-194/",
    "title": "321-194 State advisory commission"
}

        ,
      
        
{
    "path": "https://sammade.github.io/aloha-io/title-19/chapter-321/section-321-195/",
    "title": "321-195 Annual report to the legislature"
}

        ,
      
        
{
    "path": "https://sammade.github.io/aloha-io/title-19/chapter-321/section-321-196/",
    "title": "321-196 Rules"
}

        ,
      
        
{
    "path": "https://sammade.github.io/aloha-io/title-19/chapter-321/section-321-197/",
    "title": "321-197 Personnel"
}

        ,
      
        
{
    "path": "https://sammade.github.io/aloha-io/title-19/chapter-321/section-321-198/",
    "title": "321-198 State funding of substance abuse agencies"
}

        ,
      
        
{
    "path": "https://sammade.github.io/aloha-io/title-19/chapter-321/section-321-201/",
    "title": "321-201 to 206 Repealed"
}

        ,
      
        
{
    "path": "https://sammade.github.io/aloha-io/title-19/chapter-321/section-321-211/",
    "title": "321-211 Definitions"
}

        ,
      
        
{
    "path": "https://sammade.github.io/aloha-io/title-19/chapter-321/section-321-212/",
    "title": "321-212 Tobacco products; possession or consumption prohibited"
}

        ,
      
        
{
    "path": "https://sammade.github.io/aloha-io/title-19/chapter-321/section-321-213/",
    "title": "321-213 Exemptions"
}

        ,
      
        
{
    "path": "https://sammade.github.io/aloha-io/title-19/chapter-321/section-321-214/",
    "title": "321-214 Enforcement; rules"
}

        ,
      
        
{
    "path": "https://sammade.github.io/aloha-io/title-19/chapter-321/section-321-221/",
    "title": "321-221 Findings and purpose"
}

        ,
      
        
{
    "path": "https://sammade.github.io/aloha-io/title-19/chapter-321/section-321-222/",
    "title": "321-222 Definitions"
}

        ,
      
        
{
    "path": "https://sammade.github.io/aloha-io/title-19/chapter-321/section-321-223/",
    "title": "321-223 State comprehensive emergency medical services system, establishment"
}

        ,
      
        
{
    "path": "https://sammade.github.io/aloha-io/title-19/chapter-321/section-321-224/",
    "title": "321-224 Department of health, functions, duties"
}

        ,
      
        
{
    "path": "https://sammade.github.io/aloha-io/title-19/chapter-321/section-321-225/",
    "title": "321-225 The state emergency medical services advisory Committee"
}

        ,
      
        
{
    "path": "https://sammade.github.io/aloha-io/title-19/chapter-321/section-321-225_5/",
    "title": "321-225.5 Fall prevention and early detection coordinator"
}

        ,
      
        
{
    "path": "https://sammade.github.io/aloha-io/title-19/chapter-321/section-321-226/",
    "title": "321-226 Emergency medical services and systems, standards"
}

        ,
      
        
{
    "path": "https://sammade.github.io/aloha-io/title-19/chapter-321/section-321-227/",
    "title": "321-227 Regulation of ambulances"
}

        ,
      
        
{
    "path": "https://sammade.github.io/aloha-io/title-19/chapter-321/section-321-228/",
    "title": "321-228 Emergency medical services; counties"
}

        ,
      
        
{
    "path": "https://sammade.github.io/aloha-io/title-19/chapter-321/section-321-228_5/",
    "title": "321-228.5 Renumbered"
}

        ,
      
        
{
    "path": "https://sammade.github.io/aloha-io/title-19/chapter-321/section-321-228_6/",
    "title": "321-228.6 Renumbered"
}

        ,
      
        
{
    "path": "https://sammade.github.io/aloha-io/title-19/chapter-321/section-321-229/",
    "title": "321-229 Emergency medical services personnel, training programs"
}

        ,
      
        
{
    "path": "https://sammade.github.io/aloha-io/title-19/chapter-321/section-321-229_5/",
    "title": "321-229.5 Renumbered"
}

        ,
      
        
{
    "path": "https://sammade.github.io/aloha-io/title-19/chapter-321/section-321-230/",
    "title": "321-230 Technical assistance, data collection, evaluation"
}

        ,
      
        
{
    "path": "https://sammade.github.io/aloha-io/title-19/chapter-321/section-321-231/",
    "title": "321-231 Grants"
}

        ,
      
        
{
    "path": "https://sammade.github.io/aloha-io/title-19/chapter-321/section-321-232/",
    "title": "321-232 Revenues; deposit into state general fund"
}

        ,
      
        
{
    "path": "https://sammade.github.io/aloha-io/title-19/chapter-321/section-321-233/",
    "title": "321-233 Rules"
}

        ,
      
        
{
    "path": "https://sammade.github.io/aloha-io/title-19/chapter-321/section-321-234/",
    "title": "321-234 Emergency medical services special fund"
}

        ,
      
        
{
    "path": "https://sammade.github.io/aloha-io/title-19/chapter-321/section-321-235/",
    "title": "321-235 Immunity and limitation on liability for emergency aeromedical services"
}

        ,
      
        
{
    "path": "https://sammade.github.io/aloha-io/title-19/chapter-321/section-321-236/",
    "title": "321-236 Emergency medical services; use of latex gloves prohibited"
}

        ,
      
        
{
    "path": "https://sammade.github.io/aloha-io/title-19/chapter-321/section-321-241/",
    "title": "321-241 to 246 Repealed"
}

        ,
      
        
{
    "path": "https://sammade.github.io/aloha-io/title-19/chapter-321/section-321-241_5/",
    "title": "Chapter 321 Department of Health"
}

        ,
      
        
{
    "path": "https://sammade.github.io/aloha-io/title-19/chapter-321/section-321-242/",
    "title": "Chapter 321 Department of Health"
}

        ,
      
        
{
    "path": "https://sammade.github.io/aloha-io/title-19/chapter-321/section-321-243/",
    "title": "Chapter 321 Department of Health"
}

        ,
      
        
{
    "path": "https://sammade.github.io/aloha-io/title-19/chapter-321/section-321-244/",
    "title": "Chapter 321 Department of Health"
}

        ,
      
        
{
    "path": "https://sammade.github.io/aloha-io/title-19/chapter-321/section-321-245/",
    "title": "Chapter 321 Department of Health"
}

        ,
      
        
{
    "path": "https://sammade.github.io/aloha-io/title-19/chapter-321/section-321-246/",
    "title": "Chapter 321 Department of Health"
}

        ,
      
        
{
    "path": "https://sammade.github.io/aloha-io/title-19/chapter-321/section-321-261/",
    "title": "321-261 to 271 Repealed"
}

        ,
      
        
{
    "path": "https://sammade.github.io/aloha-io/title-19/chapter-321/section-321-281/",
    "title": "321-281 Financial assistance fund for hemophilia"
}

        ,
      
        
{
    "path": "https://sammade.github.io/aloha-io/title-19/chapter-321/section-321-282/",
    "title": "321-282 General duties of the department"
}

        ,
      
        
{
    "path": "https://sammade.github.io/aloha-io/title-19/chapter-321/section-321-291/",
    "title": "321-291 Tests for phenylketonuria, hypothyroidism, and other metabolic diseases"
}

        ,
      
        
{
    "path": "https://sammade.github.io/aloha-io/title-19/chapter-321/section-321-296/",
    "title": "321-296 Newborn pulse oximetry screening"
}

        ,
      
        
{
    "path": "https://sammade.github.io/aloha-io/title-19/chapter-321/section-321-301/",
    "title": "321-301 Bilingual health education aide program; establishment"
}

        ,
      
        
{
    "path": "https://sammade.github.io/aloha-io/title-19/chapter-321/section-321-311/",
    "title": "321-311 Environmentally-related illness and injury surveillance"
}

        ,
      
        
{
    "path": "https://sammade.github.io/aloha-io/title-19/chapter-321/section-321-311_5/",
    "title": "321-311.5 Renumbered"
}

        ,
      
        
{
    "path": "https://sammade.github.io/aloha-io/title-19/chapter-321/section-321-312/",
    "title": "321-312 Definition of environmentally-related illness or injury"
}

        ,
      
        
{
    "path": "https://sammade.github.io/aloha-io/title-19/chapter-321/section-321-313/",
    "title": "321-313 Definition of health care professional"
}

        ,
      
        
{
    "path": "https://sammade.github.io/aloha-io/title-19/chapter-321/section-321-314/",
    "title": "321-314 Reports to the department"
}

        ,
      
        
{
    "path": "https://sammade.github.io/aloha-io/title-19/chapter-321/section-321-315/",
    "title": "321-315 Confidentiality"
}

        ,
      
        
{
    "path": "https://sammade.github.io/aloha-io/title-19/chapter-321/section-321-316/",
    "title": "321-316 Immunity from liability"
}

        ,
      
        
{
    "path": "https://sammade.github.io/aloha-io/title-19/chapter-321/section-321-317/",
    "title": "321-317 Rules"
}

        ,
      
        
{
    "path": "https://sammade.github.io/aloha-io/title-19/chapter-321/section-321-321/",
    "title": "321-321 Purpose"
}

        ,
      
        
{
    "path": "https://sammade.github.io/aloha-io/title-19/chapter-321/section-321-322/",
    "title": "321-322 Administration of programs"
}

        ,
      
        
{
    "path": "https://sammade.github.io/aloha-io/title-19/chapter-321/section-321-323/",
    "title": "321-323 Definitions"
}

        ,
      
        
{
    "path": "https://sammade.github.io/aloha-io/title-19/chapter-321/section-321-324/",
    "title": "321-324 Powers of the department"
}

        ,
      
        
{
    "path": "https://sammade.github.io/aloha-io/title-19/chapter-321/section-321-325/",
    "title": "321-325 Agreements"
}

        ,
      
        
{
    "path": "https://sammade.github.io/aloha-io/title-19/chapter-321/section-321-326/",
    "title": "321-326 Rules"
}

        ,
      
        
{
    "path": "https://sammade.github.io/aloha-io/title-19/chapter-321/section-321-327/",
    "title": "Chapter 321 Department of Health"
}

        ,
      
        
{
    "path": "https://sammade.github.io/aloha-io/title-19/chapter-321/section-321-331/",
    "title": "321-331 Prenatal health care; authority"
}

        ,
      
        
{
    "path": "https://sammade.github.io/aloha-io/title-19/chapter-321/section-321-341/",
    "title": "321-341 Multidisciplinary and multiagency reviews"
}

        ,
      
        
{
    "path": "https://sammade.github.io/aloha-io/title-19/chapter-321/section-321-342/",
    "title": "321-342 Definitions"
}

        ,
      
        
{
    "path": "https://sammade.github.io/aloha-io/title-19/chapter-321/section-321-343/",
    "title": "321-343 Access to information; use of child death review information; protections"
}

        ,
      
        
{
    "path": "https://sammade.github.io/aloha-io/title-19/chapter-321/section-321-344/",
    "title": "321-344 Exception"
}

        ,
      
        
{
    "path": "https://sammade.github.io/aloha-io/title-19/chapter-321/section-321-345/",
    "title": "321-345 Repealed"
}

        ,
      
        
{
    "path": "https://sammade.github.io/aloha-io/title-19/chapter-321/section-321-345_5/",
    "title": "321-345.5 Child death reviews; reports"
}

        ,
      
        
{
    "path": "https://sammade.github.io/aloha-io/title-19/chapter-321/section-321-346/",
    "title": "321-346 Immunity from liability"
}

        ,
      
        
{
    "path": "https://sammade.github.io/aloha-io/title-19/chapter-321/section-321-351/",
    "title": "321-351 Definitions"
}

        ,
      
        
{
    "path": "https://sammade.github.io/aloha-io/title-19/chapter-321/section-321-352/",
    "title": "321-352 Early intervention services for infants and toddlers with special needs"
}

        ,
      
        
{
    "path": "https://sammade.github.io/aloha-io/title-19/chapter-321/section-321-352_2/",
    "title": "321-352.2 Early language services for children who are deaf, hard of hearing, or deaf-blind"
}

        ,
      
        
{
    "path": "https://sammade.github.io/aloha-io/title-19/chapter-321/section-321-353/",
    "title": "321-353 Hawaii early intervention coordinating council; establishment"
}

        ,
      
        
{
    "path": "https://sammade.github.io/aloha-io/title-19/chapter-321/section-321-354/",
    "title": "321-354 Rules"
}

        ,
      
        
{
    "path": "https://sammade.github.io/aloha-io/title-19/chapter-321/section-321-355/",
    "title": "321-355 Early intervention special fund"
}

        ,
      
        
{
    "path": "https://sammade.github.io/aloha-io/title-19/chapter-321/section-321-356/",
    "title": "321-356 Repealed"
}

        ,
      
        
{
    "path": "https://sammade.github.io/aloha-io/title-19/chapter-321/section-321-357/",
    "title": "321-357 Early intervention fund; purpose and use"
}

        ,
      
        
{
    "path": "https://sammade.github.io/aloha-io/title-19/chapter-321/section-321-361/",
    "title": "321-361 Definitions"
}

        ,
      
        
{
    "path": "https://sammade.github.io/aloha-io/title-19/chapter-321/section-321-362/",
    "title": "321-362 Duties"
}

        ,
      
        
{
    "path": "https://sammade.github.io/aloha-io/title-19/chapter-321/section-321-362_5/",
    "title": "321-362.5 Screening for hearing impairment"
}

        ,
      
        
{
    "path": "https://sammade.github.io/aloha-io/title-19/chapter-321/section-321-363/",
    "title": "321-363 Rules"
}

        ,
      
        
{
    "path": "https://sammade.github.io/aloha-io/title-19/chapter-321/section-321-371/",
    "title": "321-371 Purpose"
}

        ,
      
        
{
    "path": "https://sammade.github.io/aloha-io/title-19/chapter-321/section-321-372/",
    "title": "321-372 Definitions"
}

        ,
      
        
{
    "path": "https://sammade.github.io/aloha-io/title-19/chapter-321/section-321-373/",
    "title": "321-373 Regulation of tattoo artists"
}

        ,
      
        
{
    "path": "https://sammade.github.io/aloha-io/title-19/chapter-321/section-321-373_5/",
    "title": "321-373.5 Permit; required for tattoo shop and temporary locations"
}

        ,
      
        
{
    "path": "https://sammade.github.io/aloha-io/title-19/chapter-321/section-321-374/",
    "title": "321-374 License required; exemptions"
}

        ,
      
        
{
    "path": "https://sammade.github.io/aloha-io/title-19/chapter-321/section-321-375/",
    "title": "321-375 Examination; fees required"
}

        ,
      
        
{
    "path": "https://sammade.github.io/aloha-io/title-19/chapter-321/section-321-376/",
    "title": "321-376 Repealed"
}

        ,
      
        
{
    "path": "https://sammade.github.io/aloha-io/title-19/chapter-321/section-321-377/",
    "title": "321-377 Suspension or revocation of permit or license"
}

        ,
      
        
{
    "path": "https://sammade.github.io/aloha-io/title-19/chapter-321/section-321-378/",
    "title": "321-378 Repealed"
}

        ,
      
        
{
    "path": "https://sammade.github.io/aloha-io/title-19/chapter-321/section-321-379/",
    "title": "321-379 Enforcement; penalties"
}

        ,
      
        
{
    "path": "https://sammade.github.io/aloha-io/title-19/chapter-321/section-321-380/",
    "title": "321-380 Repealed"
}

        ,
      
        
{
    "path": "https://sammade.github.io/aloha-io/title-19/chapter-321/section-321-381/",
    "title": "321-381 Biennial renewal; failure to renew"
}

        ,
      
        
{
    "path": "https://sammade.github.io/aloha-io/title-19/chapter-321/section-321-382/",
    "title": "321-382 Fees"
}

        ,
      
        
{
    "path": "https://sammade.github.io/aloha-io/title-19/chapter-321/section-321-383/",
    "title": "321-383 Repealed"
}

        ,
      
        
{
    "path": "https://sammade.github.io/aloha-io/title-19/chapter-321/section-321-391/",
    "title": "321-391 to 398 Repealed"
}

        ,
      
        
{
    "path": "https://sammade.github.io/aloha-io/title-19/chapter-321/section-321-401/",
    "title": "321-401 Findings and purpose"
}

        ,
      
        
{
    "path": "https://sammade.github.io/aloha-io/title-19/chapter-321/section-321-402/",
    "title": "321-402 Food safety consultative and education program"
}

        ,
      
        
{
    "path": "https://sammade.github.io/aloha-io/title-19/chapter-321/section-321-403/",
    "title": "321-403 Food safety control system"
}

        ,
      
        
{
    "path": "https://sammade.github.io/aloha-io/title-19/chapter-321/section-321-404/",
    "title": "321-404 Public information monitoring system"
}

        ,
      
        
{
    "path": "https://sammade.github.io/aloha-io/title-19/chapter-321/section-321-405/",
    "title": "321-405 Confidentiality of information"
}

        ,
      
        
{
    "path": "https://sammade.github.io/aloha-io/title-19/chapter-321/section-321-411/",
    "title": "321-411 Definitions"
}

        ,
      
        
{
    "path": "https://sammade.github.io/aloha-io/title-19/chapter-321/section-321-412/",
    "title": "321-412 Indoor air quality program"
}

        ,
      
        
{
    "path": "https://sammade.github.io/aloha-io/title-19/chapter-321/section-321-413/",
    "title": "321-413 General functions, powers, and duties of the department"
}

        ,
      
        
{
    "path": "https://sammade.github.io/aloha-io/title-19/chapter-321/section-321-421/",
    "title": "321-421 Definitions"
}

        ,
      
        
{
    "path": "https://sammade.github.io/aloha-io/title-19/chapter-321/section-321-422/",
    "title": "321-422 Birth defects program"
}

        ,
      
        
{
    "path": "https://sammade.github.io/aloha-io/title-19/chapter-321/section-321-423/",
    "title": "321-423 Confidentiality of data"
}

        ,
      
        
{
    "path": "https://sammade.github.io/aloha-io/title-19/chapter-321/section-321-424/",
    "title": "321-424 Rules"
}

        ,
      
        
{
    "path": "https://sammade.github.io/aloha-io/title-19/chapter-321/section-321-425/",
    "title": "321-425 Requests for information"
}

        ,
      
        
{
    "path": "https://sammade.github.io/aloha-io/title-19/chapter-321/section-321-426/",
    "title": "321-426 Birth defects special fund"
}

        ,
      
        
{
    "path": "https://sammade.github.io/aloha-io/title-19/chapter-321/section-321-431/",
    "title": "321-431 Definitions"
}

        ,
      
        
{
    "path": "https://sammade.github.io/aloha-io/title-19/chapter-321/section-321-432/",
    "title": "321-432 Case management services for medically fragile children"
}

        ,
      
        
{
    "path": "https://sammade.github.io/aloha-io/title-19/chapter-321/section-321-441/",
    "title": "321-441 Definitions"
}

        ,
      
        
{
    "path": "https://sammade.github.io/aloha-io/title-19/chapter-321/section-321-442/",
    "title": "321-442 Exemption from certain laws and rules"
}

        ,
      
        
{
    "path": "https://sammade.github.io/aloha-io/title-19/chapter-321/section-321-471/",
    "title": "321-471 Definitions"
}

        ,
      
        
{
    "path": "https://sammade.github.io/aloha-io/title-19/chapter-321/section-321-472/",
    "title": "321-472 Multidisciplinary and multiagency reviews"
}

        ,
      
        
{
    "path": "https://sammade.github.io/aloha-io/title-19/chapter-321/section-321-473/",
    "title": "321-473 Access to information"
}

        ,
      
        
{
    "path": "https://sammade.github.io/aloha-io/title-19/chapter-321/section-321-474/",
    "title": "321-474 Exception"
}

        ,
      
        
{
    "path": "https://sammade.github.io/aloha-io/title-19/chapter-321/section-321-475/",
    "title": "321-475 Use of domestic violence fatality review information and records"
}

        ,
      
        
{
    "path": "https://sammade.github.io/aloha-io/title-19/chapter-321/section-321-476/",
    "title": "321-476 Immunity from liability"
}

        ,
      
        
{
    "path": "https://sammade.github.io/aloha-io/title-19/chapter-321/section-321-481/",
    "title": "321-481 Definitions"
}

        ,
      
        
{
    "path": "https://sammade.github.io/aloha-io/title-19/chapter-321/section-321-482/",
    "title": "321-482 Home and community-based case management agency, authority over and evaluation of"
}

        ,
      
        
{
    "path": "https://sammade.github.io/aloha-io/title-19/chapter-321/section-321-483/",
    "title": "321-483 Community care foster family home, authority over and evaluation of"
}

        ,
      
        
{
    "path": "https://sammade.github.io/aloha-io/title-19/chapter-321/section-321-484/",
    "title": "321-484 Repealed"
}

        ,
      
        
{
    "path": "https://sammade.github.io/aloha-io/title-19/chapter-321/section-321-485/",
    "title": "321-485 Penalty"
}

        ,
      
        
{
    "path": "https://sammade.github.io/aloha-io/title-19/chapter-321/section-321-491/",
    "title": "321-491 Purpose"
}

        ,
      
        
{
    "path": "https://sammade.github.io/aloha-io/title-19/chapter-321/section-321-492/",
    "title": "321-492 Definitions"
}

        ,
      
        
{
    "path": "https://sammade.github.io/aloha-io/title-19/chapter-321/section-321-493/",
    "title": "321-493 Day care centers for disabled and aged persons"
}

        ,
      
        
{
    "path": "https://sammade.github.io/aloha-io/title-19/chapter-321/section-321-494/",
    "title": "321-494 Purchase of service"
}

        ,
      
        
{
    "path": "https://sammade.github.io/aloha-io/title-19/chapter-321/section-321-495/",
    "title": "321-495 Penalty"
}

        ,
      
        
{
    "path": "https://sammade.github.io/aloha-io/title-19/chapter-321/section-321-496/",
    "title": "321-496 Repealed"
}

        ,
      
        
{
    "path": "https://sammade.github.io/aloha-io/title-19/chapter-321/section-321-501/",
    "title": "321-501 Multidisciplinary and multiagency mortality reviews"
}

        ,
      
        
{
    "path": "https://sammade.github.io/aloha-io/title-19/chapter-321/section-321-502/",
    "title": "321-502 Definitions"
}

        ,
      
        
{
    "path": "https://sammade.github.io/aloha-io/title-19/chapter-321/section-321-503/",
    "title": "321-503 Access to information"
}

        ,
      
        
{
    "path": "https://sammade.github.io/aloha-io/title-19/chapter-321/section-321-504/",
    "title": "321-504 Exception"
}

        ,
      
        
{
    "path": "https://sammade.github.io/aloha-io/title-19/chapter-321/section-321-505/",
    "title": "321-505 Use of information and records from mortality reviews of deaths of persons with developmental or intellectual disabilities"
}

        ,
      
        
{
    "path": "https://sammade.github.io/aloha-io/title-19/chapter-321/section-321-506/",
    "title": "321-506 Immunity from liability"
}

        ,
      
        
{
    "path": "https://sammade.github.io/aloha-io/title-19/chapter-321/section-321-511/",
    "title": "321-511 Definitions"
}

        ,
      
        
{
    "path": "https://sammade.github.io/aloha-io/title-19/chapter-321/section-321-512/",
    "title": "321-512 Compassionate care"
}

        ,
      
        
{
    "path": "https://sammade.github.io/aloha-io/title-19/chapter-321/section-321-513/",
    "title": "321-513 Enforcement; administrative penalties"
}

        ,
      
        
{
    "path": "https://sammade.github.io/aloha-io/title-19/chapter-321/section-321-514/",
    "title": "321-514 Rules"
}

        ,
      
        
{
    "path": "https://sammade.github.io/aloha-io/title-19/chapter-321/section-321-531/",
    "title": "321-531 Definitions"
}

        ,
      
        
{
    "path": "https://sammade.github.io/aloha-io/title-19/chapter-321/section-321-532/",
    "title": "321-532 Stroke system of care; department duties"
}

        ,
      
        
{
    "path": "https://sammade.github.io/aloha-io/title-19/chapter-321/section-321-533/",
    "title": "321-533 Stroke database"
}

        ,
      
        
{
    "path": "https://sammade.github.io/aloha-io/title-19/chapter-321/section-321-534/",
    "title": "321-534 Confidential information"
}

        ,
      
        
{
    "path": "https://sammade.github.io/aloha-io/title-19/chapter-321/section-321-541/",
    "title": "321-541 Title"
}

        ,
      
        
{
    "path": "https://sammade.github.io/aloha-io/title-19/chapter-321/section-321-542/",
    "title": "321-542 Definitions"
}

        ,
      
        
{
    "path": "https://sammade.github.io/aloha-io/title-19/chapter-321/section-321-543/",
    "title": "321-543 Licensing"
}

        ,
      
        
{
    "path": "https://sammade.github.io/aloha-io/title-19/chapter-321/section-321-544/",
    "title": "321-544 License fee"
}

        ,
      
        
{
    "path": "https://sammade.github.io/aloha-io/title-19/chapter-321/section-321-545/",
    "title": "321-545 Exemptions"
}

        ,
      
        
{
    "path": "https://sammade.github.io/aloha-io/title-19/chapter-321/section-321-546/",
    "title": "321-546 Rules"
}

        ,
      
        
{
    "path": "https://sammade.github.io/aloha-io/title-19/chapter-321/section-321-547/",
    "title": "321-547 Severability"
}

        
      
    
  ]
}



