{
  "path": "/aloha-io/title-20/chapter-353/section-353-34/",
  "title": "Probation services fee; assessment",
  "type": "hrs_section",
  "structure": {
    "volume": "7",
    "chapter": "353",
    "section": "353-34"
  },
  
  "prev": "https://sammade.github.io/aloha-io/title-20/chapter-353/section-353-33/",
  
  
  "next": "https://sammade.github.io/aloha-io/title-20/chapter-353/section-353-35/",
  
  "context": "ยง353-34 Probation services fee; assessment. Any defendant received for supervision pursuant to chapter 353B shall be assessed a probation services fee pursuant to section 706-648. [L 2000, c 205, ยง1; am L 2004, c 78, ยง1] "
}