{
  "path": "https://sammade.github.io/aloha-io/title-12/chapter-181/",
  "title": "Strip Mining",
  "volume": "12",
  "chapter": "181",
  "section": "",
  "context": "SUBTITLE 3. MINING AND MINERALS CHAPTER 181 STRIP MINING Section 181-1 Definitions 181-2 Powers of board 181-3 Prohibitions 181-4 Application for permit; fee 181-5 Bond 181-6 Reclamation 181-7 Termination, revocation of permit; release 181-8 Appeal 181-9 Penalty; injunction 181-10 Funds Cross References Environmental courts, jurisdiction over proceedings arising under this chapter, see ยง604A-2. ",
  "children" : [
    

    
      
      
      
      
      
        
{
    "path": "https://sammade.github.io/aloha-io/title-12/chapter-181/section-181-1/",
    "title": "181-1 Definitions"
}

        ,
      
        
{
    "path": "https://sammade.github.io/aloha-io/title-12/chapter-181/section-181-2/",
    "title": "181-2 Powers of board"
}

        ,
      
        
{
    "path": "https://sammade.github.io/aloha-io/title-12/chapter-181/section-181-3/",
    "title": "181-3 Prohibitions"
}

        ,
      
        
{
    "path": "https://sammade.github.io/aloha-io/title-12/chapter-181/section-181-4/",
    "title": "181-4 Application for permit; fee"
}

        ,
      
        
{
    "path": "https://sammade.github.io/aloha-io/title-12/chapter-181/section-181-5/",
    "title": "181-5 Bond"
}

        ,
      
        
{
    "path": "https://sammade.github.io/aloha-io/title-12/chapter-181/section-181-6/",
    "title": "181-6 Reclamation"
}

        ,
      
        
{
    "path": "https://sammade.github.io/aloha-io/title-12/chapter-181/section-181-7/",
    "title": "181-7 Termination, revocation of permit; release"
}

        ,
      
        
{
    "path": "https://sammade.github.io/aloha-io/title-12/chapter-181/section-181-8/",
    "title": "181-8 Appeal"
}

        ,
      
        
{
    "path": "https://sammade.github.io/aloha-io/title-12/chapter-181/section-181-9/",
    "title": "181-9 Penalty; injunction"
}

        ,
      
        
{
    "path": "https://sammade.github.io/aloha-io/title-12/chapter-181/section-181-10/",
    "title": "181-10 Funds"
}

        
      
    
  ]
}



