{
  "path": "/aloha-io/title-19/chapter-328/section-328-62/",
  "title": "Description of label",
  "type": "hrs_section",
  "structure": {
    "volume": "6",
    "chapter": "328",
    "section": "328-62"
  },
  
  "prev": "https://sammade.github.io/aloha-io/title-19/chapter-328/section-328-61/",
  
  
  "next": "https://sammade.github.io/aloha-io/title-19/chapter-328/section-328-63/",
  
  "context": "§328-62 Description of label. Label means the information required in this part to be placed on any food products by means of a stamp, stencil, or printing by machine, or by attaching to the immediate package, by sign, handbill, placard, or otherwise, the words PREVIOUSLY FROZEN in letter size easily seen under customary conditions of purchase. [L 1967, c 206, pt of §1; HRS §328-62; am L 1980, c 40, §3] "
}