{
  "path": "/aloha-io/title-1/chapter-8/section-8-5_5/",
  "title": "Queen Liliuokalani Day",
  "type": "hrs_section",
  "structure": {
    "volume": "1",
    "chapter": "8",
    "section": "8-5.5"
  },
  
  "prev": "https://sammade.github.io/aloha-io/title-1/chapter-8/section-8-5/",
  
  
  "next": "https://sammade.github.io/aloha-io/title-1/chapter-8/section-8-6/",
  
  "context": "[§8-5.5] Queen Liliuokalani Day. September 2 of each year shall be known and recognized as &amp;ldquo;Queen Liliuokalani Day&amp;rdquo; in memory of the birth of Queen Liliuokalani on September 2, 1838; provided that this day shall not be a state holiday. [L 1993, c 11, §1] "
}