{
  "path": "/aloha-io/title-26/chapter-482e/section-482e-11/",
  "title": "Fees",
  "type": "hrs_section",
  "structure": {
    "volume": "11",
    "chapter": "482E",
    "section": "482E-11"
  },
  
  "prev": "https://sammade.github.io/aloha-io/title-26/chapter-482e/section-482e-10_7/",
  
  
  "next": "https://sammade.github.io/aloha-io/title-26/chapter-482e/section-482e-12/",
  
  "context": "ยง482E-11 Fees. The director shall charge and collect a fee of $250 at the time of the filing of the offering circular, a fee of $250 for the filing of any amended offering circular filed pursuant to section 482E-3&amp;copy;, and an annual renewal fee of $250 to be collected pursuant to section 482E-3(d). [L 1974, c 18, pt of ยง1; am L 1978, c 242, ยง12; am L 1996, c 181, ยง9] "
}