{
  "path": "https://sammade.github.io/aloha-io/title-24/chapter-431c/",
  "title": "Life Settlements",
  "volume": "24",
  "chapter": "431C",
  "section": "",
  "context": "[CHAPTER 431C] LIFE SETTLEMENTS Part I. General Provisions Section 431C-1 Short title 431C-2 Definitions 431C-3 Licensing requirements 431C-4 License suspension, revocation, or refusal to renew 431C-5 Contract requirements 431C-6 Reporting requirements and privacy Part II. Examinations 431C-11 Examination 431C-12 Conduct of examinations 431C-13 Examination reports 431C-14 Confidentiality of examination information 431C-15 Examiner; conflict of interest 431C-16 Immunity from liability 431C-17 Investigative authority of the commissioner Part III. Advertising 431C-21 Advertising Part IV. Disclosures and General Procedures 431C-31 Disclosures to owners 431C-32 Disclosure to insurer 431C-33 General rules 431C-34 Buyer&amp;rsquo;s guide Part V. Miscellaneous Provisions 431C-41 Prohibited practices 431C-42 Fraudulent life settlement acts prohibited 431C-43 Fraud warning required 431C-44 Mandatory reporting of fraudulent life settlement acts 431C-45 Immunity from liability 431C-46 Confidentiality 431C-47 Other law enforcement or regulatory authority 431C-48 Life settlement anti-fraud initiatives 431C-49 Injunctions; civil remedies; cease and desist 431C-50 Penalties 431C-51 Unfair trade practices 431C-52 Conflict of laws 431C-53 Authority to adopt rules ",
  "children" : [
    

    
      
      
      
      
      
        
{
    "path": "https://sammade.github.io/aloha-io/title-24/chapter-431c/section-431c-1/",
    "title": "431C-1 Short title"
}

        ,
      
        
{
    "path": "https://sammade.github.io/aloha-io/title-24/chapter-431c/section-431c-2/",
    "title": "431C-2 Definitions"
}

        ,
      
        
{
    "path": "https://sammade.github.io/aloha-io/title-24/chapter-431c/section-431c-3/",
    "title": "431C-3 Licensing requirements"
}

        ,
      
        
{
    "path": "https://sammade.github.io/aloha-io/title-24/chapter-431c/section-431c-4/",
    "title": "431C-4 License suspension, revocation, or refusal to renew"
}

        ,
      
        
{
    "path": "https://sammade.github.io/aloha-io/title-24/chapter-431c/section-431c-5/",
    "title": "431C-5 Contract requirements"
}

        ,
      
        
{
    "path": "https://sammade.github.io/aloha-io/title-24/chapter-431c/section-431c-6/",
    "title": "431C-6 Reporting requirements and privacy"
}

        ,
      
        
{
    "path": "https://sammade.github.io/aloha-io/title-24/chapter-431c/section-431c-11/",
    "title": "431C-11 Examination"
}

        ,
      
        
{
    "path": "https://sammade.github.io/aloha-io/title-24/chapter-431c/section-431c-12/",
    "title": "431C-12 Conduct of examinations"
}

        ,
      
        
{
    "path": "https://sammade.github.io/aloha-io/title-24/chapter-431c/section-431c-13/",
    "title": "431C-13 Examination reports"
}

        ,
      
        
{
    "path": "https://sammade.github.io/aloha-io/title-24/chapter-431c/section-431c-14/",
    "title": "431C-14 Confidentiality of examination information"
}

        ,
      
        
{
    "path": "https://sammade.github.io/aloha-io/title-24/chapter-431c/section-431c-15/",
    "title": "431C-15 Examiner; conflict of interest"
}

        ,
      
        
{
    "path": "https://sammade.github.io/aloha-io/title-24/chapter-431c/section-431c-16/",
    "title": "431C-16 Immunity from liability"
}

        ,
      
        
{
    "path": "https://sammade.github.io/aloha-io/title-24/chapter-431c/section-431c-17/",
    "title": "431C-17 Investigative authority of the commissioner"
}

        ,
      
        
{
    "path": "https://sammade.github.io/aloha-io/title-24/chapter-431c/section-431c-21/",
    "title": "431C-21 Advertising"
}

        ,
      
        
{
    "path": "https://sammade.github.io/aloha-io/title-24/chapter-431c/section-431c-31/",
    "title": "431C-31 Disclosures to owners"
}

        ,
      
        
{
    "path": "https://sammade.github.io/aloha-io/title-24/chapter-431c/section-431c-32/",
    "title": "431C-32 Disclosure to insurer"
}

        ,
      
        
{
    "path": "https://sammade.github.io/aloha-io/title-24/chapter-431c/section-431c-33/",
    "title": "431C-33 General rules"
}

        ,
      
        
{
    "path": "https://sammade.github.io/aloha-io/title-24/chapter-431c/section-431c-34/",
    "title": "431C-34 Buyer&#39;s guide"
}

        ,
      
        
{
    "path": "https://sammade.github.io/aloha-io/title-24/chapter-431c/section-431c-41/",
    "title": "431C-41 Prohibited practices"
}

        ,
      
        
{
    "path": "https://sammade.github.io/aloha-io/title-24/chapter-431c/section-431c-42/",
    "title": "431C-42 Fraudulent life settlement acts prohibited"
}

        ,
      
        
{
    "path": "https://sammade.github.io/aloha-io/title-24/chapter-431c/section-431c-43/",
    "title": "431C-43 Fraud warning required"
}

        ,
      
        
{
    "path": "https://sammade.github.io/aloha-io/title-24/chapter-431c/section-431c-44/",
    "title": "431C-44 Mandatory reporting of fraudulent life settlement"
}

        ,
      
        
{
    "path": "https://sammade.github.io/aloha-io/title-24/chapter-431c/section-431c-45/",
    "title": "431C-45 Immunity from liability"
}

        ,
      
        
{
    "path": "https://sammade.github.io/aloha-io/title-24/chapter-431c/section-431c-46/",
    "title": "431C-46 Confidentiality"
}

        ,
      
        
{
    "path": "https://sammade.github.io/aloha-io/title-24/chapter-431c/section-431c-47/",
    "title": "431C-47 Other law enforcement or regulatory authority"
}

        ,
      
        
{
    "path": "https://sammade.github.io/aloha-io/title-24/chapter-431c/section-431c-48/",
    "title": "431C-48 Life settlement anti-fraud initiatives"
}

        ,
      
        
{
    "path": "https://sammade.github.io/aloha-io/title-24/chapter-431c/section-431c-49/",
    "title": "431C-49 Injunctions; civil remedies; cease and desist"
}

        ,
      
        
{
    "path": "https://sammade.github.io/aloha-io/title-24/chapter-431c/section-431c-50/",
    "title": "431C-50 Penalties"
}

        ,
      
        
{
    "path": "https://sammade.github.io/aloha-io/title-24/chapter-431c/section-431c-51/",
    "title": "431C-51 Unfair trade practices"
}

        ,
      
        
{
    "path": "https://sammade.github.io/aloha-io/title-24/chapter-431c/section-431c-52/",
    "title": "431C-52 Conflict of laws"
}

        ,
      
        
{
    "path": "https://sammade.github.io/aloha-io/title-24/chapter-431c/section-431c-53/",
    "title": "431C-53 Authority to adopt rules"
}

        
      
    
  ]
}



