{
  "path": "/aloha-io/title-23/chapter-414d/section-414d-144/",
  "title": "Action without meeting",
  "type": "hrs_section",
  "structure": {
    "volume": "8",
    "chapter": "414D",
    "section": "414D-144"
  },
  
  "prev": "https://sammade.github.io/aloha-io/title-23/chapter-414d/section-414d-143/",
  
  
  "next": "https://sammade.github.io/aloha-io/title-23/chapter-414d/section-414d-145/",
  
  "context": "[ยง414D-144] Action without meeting. (a) Unless the articles or bylaws provide otherwise, action required or permitted by this chapter to be taken at a board of directors&amp;rsquo; meeting may be taken without a meeting if the action is taken by all members of the board. The action must be evidenced by one or more written consents describing the action taken, signed by each director, and included in the minutes filed with the corporate records reflecting the action taken. (b) Action taken under this section is effective when the last director signs the consent, unless the consent specifies a different effective date. &amp;copy; A consent signed under this section has the effect of a meeting vote and may be described as such in any document. [L 2001, c 105, pt of ยง1] "
}